LICENSE.txt
MANIFEST.in
README.rst
requirements.txt
setup.py
python_kafka_logger.egg-info/PKG-INFO
python_kafka_logger.egg-info/SOURCES.txt
python_kafka_logger.egg-info/dependency_links.txt
python_kafka_logger.egg-info/not-zip-safe
python_kafka_logger.egg-info/requires.txt
python_kafka_logger.egg-info/top_level.txt
python_kafka_logging/KafkaHandler.py
python_kafka_logging/__init__.py