Metadata-Version: 1.1
Name: python-kafka-logger
Version: 0.4
Summary: Simple python logging handler for forwarding logs to a kafka server.
Home-page: https://github.com/avihoo/python-kafka-logging
Author: Avihoo Mamka
Author-email: avihoo.mamka@gmail.com
License: Apache 2.0
Keywords: python,logging,handler,example,kafka,logs,logstash,formatter
Platform: UNKNOWN
Classifier: Intended Audience :: Developers
Classifier: Natural Language :: English
Classifier: License :: OSI Approved :: Apache Software License
Classifier: Programming Language :: Python
Classifier: Programming Language :: Python :: 2.7
